JaqalPaq_dev-1.1.0b1.data/data/share/jaqalpaq/examples/usage_example.py
JaqalPaq_dev-1.1.0b1.data/data/share/jaqalpaq/examples/H2 (Molecular Hydrogen)/JaqalPaq_H2_Exemplar.ipynb
JaqalPaq_dev-1.1.0b1.data/data/share/jaqalpaq/examples/HeH+ (Helium Hydride)/JaqalPaq_HeH+_Tapered_Exemplar.ipynb
JaqalPaq_dev-1.1.0b1.data/data/share/jaqalpaq/examples/HeH+ (Helium Hydride)/JaqalPaq_HeH+_Untapered_Exemplar.ipynb
JaqalPaq_dev-1.1.0b1.data/data/share/jaqalpaq/examples/LiH (Lithium Hydride)/JaqalPaq_LiH_Exemplar.ipynb
JaqalPaq_dev-1.1.0b1.data/data/share/jaqalpaq/examples/Tutorials/Emulator_Demo.ipynb
JaqalPaq_dev-1.1.0b1.data/data/share/jaqalpaq/examples/jaqal/Sxx_circuit.jaqal
JaqalPaq_dev-1.1.0b1.data/data/share/jaqalpaq/examples/jaqal/Sxx_circuit_q.py
JaqalPaq_dev-1.1.0b1.data/data/share/jaqalpaq/examples/jaqal/bell_prep.jaqal
JaqalPaq_dev-1.1.0b1.data/data/share/jaqalpaq/examples/jaqal/bell_prep.py
JaqalPaq_dev-1.1.0b1.data/data/share/jaqalpaq/examples/jaqal/bell_prep_q.py
JaqalPaq_dev-1.1.0b1.data/data/share/jaqalpaq/examples/jaqal/bell_prep_spec.jaqal
JaqalPaq_dev-1.1.0b1.data/data/share/jaqalpaq/examples/jaqal/empty_loop.jaqal
JaqalPaq_dev-1.1.0b1.data/data/share/jaqalpaq/examples/jaqal/empty_loop_outside_subcircuit.jaqal
JaqalPaq_dev-1.1.0b1.data/data/share/jaqalpaq/examples/jaqal/empty_loop_q.py
JaqalPaq_dev-1.1.0b1.data/data/share/jaqalpaq/examples/jaqal/empty_parallel.jaqal
JaqalPaq_dev-1.1.0b1.data/data/share/jaqalpaq/examples/jaqal/empty_parallel_q.py
JaqalPaq_dev-1.1.0b1.data/data/share/jaqalpaq/examples/jaqal/empty_prog.jaqal
JaqalPaq_dev-1.1.0b1.data/data/share/jaqalpaq/examples/jaqal/empty_prog_q.py
JaqalPaq_dev-1.1.0b1.data/data/share/jaqalpaq/examples/jaqal/idle_padding.jaqal
JaqalPaq_dev-1.1.0b1.data/data/share/jaqalpaq/examples/jaqal/idle_padding_q.py
JaqalPaq_dev-1.1.0b1.data/data/share/jaqalpaq/examples/jaqal/molmer-sorensen-rotations.jaqal
JaqalPaq_dev-1.1.0b1.data/data/share/jaqalpaq/examples/jaqal/molmer-sorensen-rotations_q.py
JaqalPaq_dev-1.1.0b1.dist-info/LICENSE
JaqalPaq_dev-1.1.0b1.dist-info/METADATA
JaqalPaq_dev-1.1.0b1.dist-info/NOTICE
JaqalPaq_dev-1.1.0b1.dist-info/WHEEL
JaqalPaq_dev-1.1.0b1.dist-info/entry_points.txt
JaqalPaq_dev-1.1.0b1.dist-info/top_level.txt
JaqalPaq_dev-1.1.0b1.dist-info/RECORD
