Metadata-Version: 2.1
Name: JaqalPaq-dev
Version: 1.1.0b1
Summary: Python tools for Jaqal
Home-page: https://qscout.sandia.gov
Author: Benjamin C. A. Morrison, Jay Wesley Van Der Wall, Daniel Lobser, Antonio Russo, Kenneth Rudinger, Peter Maunz
Author-email: qscout@sandia.gov
License: Apache
Classifier: Development Status :: 4 - Beta
Classifier: Intended Audience :: Science/Research
Classifier: License :: OSI Approved :: Apache Software License
Classifier: Programming Language :: Python :: 3
Classifier: Topic :: Scientific/Engineering :: Physics
Classifier: Operating System :: Microsoft :: Windows
Classifier: Operating System :: MacOS :: MacOS X
Classifier: Operating System :: Unix
Requires-Python: >=3.6.5
License-File: LICENSE
License-File: NOTICE
Requires-Dist: sly
Provides-Extra: docs
Requires-Dist: Sphinx ; extra == 'docs'
Requires-Dist: sphinx-rtd-theme ; extra == 'docs'
Requires-Dist: JaqalPaq-dev[pygsti-integration] ; extra == 'docs'
Requires-Dist: JaqalPaq-extras-dev[projectq,pyquil,pytket,qiskit] (==1.1.0b1) ; extra == 'docs'
Provides-Extra: notebooks
Requires-Dist: openfermion (==1.1.0) ; extra == 'notebooks'
Requires-Dist: pyscf (<1.7.7,>=1.7.6) ; extra == 'notebooks'
Requires-Dist: openfermionpyscf (==0.5) ; extra == 'notebooks'
Requires-Dist: h5py (<3.3) ; extra == 'notebooks'
Provides-Extra: pygsti-integration
Requires-Dist: pyGSTi (<0.9.11,>=0.9.10.1) ; extra == 'pygsti-integration'
Provides-Extra: tests
Requires-Dist: pytest ; extra == 'tests'
